[1,0,0,[["sp.SkeletonData",["_name","_atlasText","_skeletonJson"],0]],[[0,0,1,2,4]],[[0,"NPC_1_3","\r\nnpc_1_3.png\r\nsize: 795,795\r\nformat: RGBA8888\r\nfilter: Linear,Linear\r\nrepeat: none\r\n1\r\n  rotate: true\r\n  xy: 2, 2\r\n  size: 432, 209\r\n  orig: 432, 209\r\n  offset: 0, 0\r\n  index: -1\r\n10\r\n  rotate: true\r\n  xy: 374, 310\r\n  size: 124, 70\r\n  orig: 124, 70\r\n  offset: 0, 0\r\n  index: -1\r\n11\r\n  rotate: true\r\n  xy: 593, 73\r\n  size: 124, 106\r\n  orig: 124, 106\r\n  offset: 0, 0\r\n  index: -1\r\n12\r\n  rotate: true\r\n  xy: 446, 409\r\n  size: 384, 292\r\n  orig: 384, 292\r\n  offset: 0, 0\r\n  index: -1\r\n13\r\n  rotate: true\r\n  xy: 493, 53\r\n  size: 140, 98\r\n  orig: 142, 98\r\n  offset: 1, 0\r\n  index: -1\r\n14\r\n  rotate: true\r\n  xy: 308, 86\r\n  size: 89, 183\r\n  orig: 89, 183\r\n  offset: 0, 0\r\n  index: -1\r\n2\r\n  rotate: true\r\n  xy: 512, 199\r\n  size: 113, 120\r\n  orig: 114, 121\r\n  offset: 1, 0\r\n  index: -1\r\n3\r\n  rotate: true\r\n  xy: 634, 213\r\n  size: 103, 83\r\n  orig: 104, 84\r\n  offset: 0, 1\r\n  index: -1\r\n4\r\n  rotate: true\r\n  xy: 308, 177\r\n  size: 257, 64\r\n  orig: 258, 93\r\n  offset: 0, 0\r\n  index: -1\r\n4_1\r\n  rotate: true\r\n  xy: 213, 176\r\n  size: 258, 93\r\n  orig: 258, 93\r\n  offset: 0, 0\r\n  index: -1\r\n5\r\n  rotate: true\r\n  xy: 213, 13\r\n  size: 161, 87\r\n  orig: 161, 87\r\n  offset: 0, 0\r\n  index: -1\r\n6\r\n  rotate: false\r\n  xy: 2, 436\r\n  size: 442, 357\r\n  orig: 442, 357\r\n  offset: 0, 0\r\n  index: -1\r\n7\r\n  rotate: true\r\n  xy: 596, 318\r\n  size: 89, 150\r\n  orig: 89, 150\r\n  offset: 0, 0\r\n  index: -1\r\n8\r\n  rotate: true\r\n  xy: 446, 314\r\n  size: 93, 148\r\n  orig: 93, 148\r\n  offset: 0, 0\r\n  index: -1\r\n9\r\n  rotate: false\r\n  xy: 374, 195\r\n  size: 136, 113\r\n  orig: 138, 114\r\n  offset: 0, 0\r\n  index: -1\r\nmaozi\r\n  rotate: true\r\n  xy: 302, 9\r\n  size: 75, 73\r\n  orig: 312, 136\r\n  offset: 120, 25\r\n  index: -1\r\n",{"skeleton":{"hash":"wN87ShsYKzSXY3i0JE4551GKzlM","spine":"3.8.99","x":-134.37,"y":-13.55,"width":348.86,"height":397.45,"images":"","audio":"E:/2024/小狗跳舞/看跳舞2/images"},"bones":[{"name":"root","scaleX":0.5,"scaleY":0.5},{"name":"12","parent":"root","length":103.38,"rotation":111.41,"x":-50.14,"y":91.26},{"name":"13","parent":"12","length":62.7,"rotation":-63.42,"x":2.43,"y":-0.13},{"name":"14","parent":"12","length":140.86,"rotation":47.78,"x":0.72,"y":-0.28},{"name":"16","parent":"14","length":109.36,"rotation":27.69,"x":61.6,"y":89.32},{"name":"17","parent":"14","length":141.76,"rotation":112.68,"x":181.24,"y":-21.72},{"name":"13b","parent":"13","length":62.7,"x":62.7},{"name":"9","parent":"13b","length":80.35,"rotation":150.45,"x":15.54,"y":130.59},{"name":"11","parent":"9","length":72.5,"rotation":4.04,"x":78.41,"y":1.46},{"name":"2","parent":"13b","length":62.03,"rotation":-135.47,"x":150.87,"y":-84.35},{"name":"4","parent":"2","length":64.09,"rotation":-49.67,"x":68.12,"y":-0.95},{"name":"15","parent":"root","length":80.38,"rotation":91.46,"x":160.15,"y":0.35},{"name":"6","parent":"13b","length":296.74,"rotation":34.5,"x":72.46,"y":3.58},{"name":"8","parent":"6","length":45.68,"rotation":-28.26,"x":263.46,"y":-135.39},{"name":"10","parent":"8","length":49.64,"rotation":16.55,"x":45.68},{"name":"18","parent":"6","length":45.71,"rotation":38.36,"x":259.12,"y":143.3},{"name":"19","parent":"18","length":48.66,"rotation":-15.25,"x":45.71},{"name":"7","parent":"6","length":110.46,"rotation":90.15,"x":130.07,"y":4.79},{"name":"5","parent":"7","length":29.01,"rotation":-88.02,"x":2.9,"y":-13.91},{"name":"21","parent":"7","length":69.22,"rotation":-89.87,"x":2.02,"y":-45.35},{"name":"1","parent":"6","length":80.84,"rotation":3.65,"x":248.92,"y":-25.16},{"name":"maozi_1","parent":"6","rotation":-6.64,"x":413.03,"y":-19.82,"scaleX":2,"scaleY":2},{"name":"maozi_2","parent":"6","rotation":-6.64,"x":413.03,"y":-19.82,"scaleX":2,"scaleY":2}],"slots":[{"name":"maozi_2","bone":"maozi_2","attachment":"maozi"},{"name":"14","bone":"17","attachment":"14"},{"name":"13","bone":"16","attachment":"13"},{"name":"12","bone":"12","attachment":"12"},{"name":"11","bone":"15","attachment":"11"},{"name":"10","bone":"11","attachment":"10"},{"name":"9","bone":"9","attachment":"9"},{"name":"8","bone":"18","attachment":"8"},{"name":"7","bone":"8","attachment":"7"},{"name":"6","bone":"6","attachment":"6"},{"name":"5","bone":"21","attachment":"5"},{"name":"4","bone":"5","attachment":"4_1"},{"name":"3","bone":"4","attachment":"3"},{"name":"2","bone":"2","attachment":"2"},{"name":"1","bone":"1","attachment":"1"},{"name":"maozi_1","bone":"maozi_1","attachment":"maozi"}],"skins":[{"name":"default","attachments":{"1":{"1":{"type":"mesh","hull":23,"width":432,"height":209,"uvs":[0.75806,0.17065,0.84647,0.25372,0.91766,0.31779,0.92454,0.5124,0.96817,0.51477,1,0.58359,1,1,0.89354,1,0.87747,0.83041,0.88206,0.69751,0.79251,0.55274,0.63751,0.45781,0.49054,0.41747,0.32177,0.40798,0.15529,0.42459,0.03932,0.4768,0,0.55749,0,0.29169,0.02554,0.21337,0.0864,0.18964,0.16562,0.08997,0.18629,0,0.63406,0,0.91191,0.57885,0.92225,0.72836],"triangles":[13,21,22,20,21,13,12,13,22,14,19,20,14,20,13,11,22,0,12,22,11,19,17,18,15,19,14,15,17,19,10,0,1,3,10,1,3,1,2,11,0,10,16,17,15,23,10,3,9,10,23,23,5,24,4,23,3,5,23,4,9,23,24,8,9,24,7,8,24,24,5,6,7,24,6],"vertices":[50.69,-92.14,35.94,-131.42,24.65,-163,-15.73,-168.71,-14.95,-187.55,-28.37,-202.24,-115.21,-208.11,-118.31,-162.22,-83.41,-152.9,-55.56,-153.01,-27.98,-112.37,-12.7,-44.23,-8.57,19.69,-11.51,92.57,-19.82,164.09,-34.08,213.34,-52.05,229.15,3.37,232.89,20.45,222.99,27.17,197.09,50.26,164.35,69.62,156.71,82.66,-36.29,-29.95,-164.2,-60.83,-170.77],"edges":[42,40,40,38,38,36,36,34,32,34,32,30,30,28,28,26,26,24,24,22,22,20,20,18,18,16,12,14,16,14,6,8,12,10,8,10,6,4,4,2,2,0,42,44,0,44,6,46,46,48,48,14]}},"2":{"2":{"x":44.73,"y":6.6,"rotation":87.48,"width":114,"height":121}},"3":{"3":{"x":25.55,"y":3.3,"rotation":137.15,"width":104,"height":84}},"4":{"4":{"x":30.71,"y":-3.32,"rotation":-84.61,"width":258,"height":93},"4_1":{"x":30.71,"y":-3.32,"rotation":-84.61,"width":258,"height":93}},"5":{"5":{"x":31.19,"y":-5.9,"rotation":-82.76,"width":161,"height":87}},"6":{"6":{"type":"mesh","hull":25,"width":442,"height":357,"uvs":[0.80587,0.05944,0.89176,0.14392,0.95176,0.30415,0.98117,0.45709,1,0.65227,1,0.76297,0.95764,0.86639,0.88117,0.95233,0.79176,1,0.43882,1,0.26823,0.95961,0.17293,0.92902,0.09529,0.83143,0.03764,0.71491,0,0.63042,0,0.49496,0.02352,0.44398,0.03058,0.38571,0.06352,0.27793,0.10705,0.19928,0.18117,0.10605,0.25764,0.06236,0.32352,0.0274,0.42002,0,0.68705,0,0.33058,0.2692,0.72823,0.29687,0.80117,0.39009,0.87881,0.57507,0.8847,0.75569,0.78234,0.88824,0.63293,0.94067,0.45882,0.92611,0.29764,0.89261,0.17176,0.79939,0.13411,0.65519,0.15411,0.50079,0.22705,0.34493,0.50777,0.5694],"triangles":[30,31,38,38,31,32,32,33,38,38,33,35,28,38,27,28,30,38,38,36,37,37,25,38,36,38,35,38,26,27,38,25,26,8,9,31,9,32,31,31,30,8,8,30,7,10,33,9,9,33,32,10,11,33,6,7,29,12,34,11,11,34,33,7,30,29,30,28,29,6,29,5,34,12,35,12,13,35,33,34,35,29,4,5,29,28,4,13,14,35,35,14,36,28,3,4,36,15,16,36,14,15,28,27,3,16,17,36,36,17,37,37,17,18,27,2,3,2,27,1,18,19,37,19,20,37,37,20,25,27,26,1,25,23,26,23,24,26,26,0,1,26,24,0,20,21,25,21,22,25,25,22,23],"vertices":[1,12,327.53,-102.6,1,1,12,302.59,-144.18,1,1,12,249.35,-177.96,1,1,12,196.92,-197.99,1,1,12,128.93,-215.36,1,1,12,89.75,-220.53,1,1,12,50.7,-206.79,1,1,12,15.86,-177.3,1,1,12,-6.18,-140.34,1,1,12,-26.59,14.32,1,1,12,-22.16,90.96,1,1,12,-16.84,134.14,1,1,12,13.21,172.73,1,1,12,51.12,203.43,1,1,12,78.85,223.87,1,1,12,126.79,230.19,1,1,12,146.19,222.27,1,1,12,167.23,221.89,1,1,12,207.28,212.49,1,1,12,237.63,197.09,1,1,12,274.91,168.97,1,1,12,294.8,137.5,1,1,12,310.98,110.26,1,1,12,326.26,69.25,1,1,12,341.7,-47.76,1,2,12,225.81,95.88,0.504,17,90.85,-95.97,0.496,2,12,239.01,-79.67,0.504,17,-84.73,-108.72,0.496,2,12,210.23,-115.98,0.504,17,-120.97,-79.85,0.496,2,12,149.25,-158.65,0.504,17,-163.48,-18.76,0.496,2,12,85.66,-169.66,0.504,17,-174.33,44.86,0.496,2,12,32.83,-131,0.504,17,-135.54,97.59,0.496,2,12,5.63,-67.97,0.504,17,-72.44,124.62,0.496,2,12,0.72,9,0.504,17,4.55,129.34,0.496,2,12,3.26,81.2,0.504,17,76.73,126.62,0.496,2,12,28.98,140.71,0.504,17,136.18,100.75,0.496,2,12,77.84,163.94,0.504,17,159.29,51.83,0.496,2,12,133.64,162.39,0.504,17,157.59,-3.97,0.496,2,12,193.02,137.71,0.504,17,132.76,-63.28,0.496,2,12,129.8,4.21,0.104,17,-0.58,0.27,0.896],"edges":[46,44,44,42,42,40,40,38,38,36,36,34,34,32,32,30,28,30,28,26,26,24,24,22,22,20,20,18,10,12,12,14,16,18,14,16,46,48,48,0,0,2,2,4,4,6,10,8,6,8,50,52,52,54,54,56,56,58,58,60,60,62,62,64,64,66,66,68,68,70,70,72,72,74,74,50]}},"7":{"7":{"type":"mesh","hull":22,"width":89,"height":150,"uvs":[0.8328,0,0.85235,0.00515,0.95674,0.08782,0.95542,0.13064,1,0.18739,1,0.3182,1,0.48695,0.95396,0.70582,0.89646,0.97921,0.87668,1,0.86193,1,0.7825,0.89107,0.69626,0.80486,0.65212,0.80889,0.11767,0.42063,0.13582,0.37597,0,0.29205,0,0.27748,0.14542,0.22688,0.2935,0.17534,0.52377,0.0952,0.79731,0],"triangles":[6,19,5,19,20,5,4,5,20,3,20,21,21,2,3,21,0,1,20,3,4,2,21,1,9,10,8,10,11,8,8,11,7,11,12,7,12,13,7,7,13,14,7,14,15,7,15,18,7,18,6,6,18,19,15,16,18,16,17,18],"vertices":[1,14,54.66,4.13,1,1,14,54.5,2.24,1,1,14,45.85,-10.62,1,1,14,39.75,-12.63,1,1,14,33.02,-19.17,1,2,13,66.87,-20.45,0.09732,14,14.49,-25.64,0.90268,2,13,46.34,-35.25,0.69633,14,-9.41,-33.98,0.30367,2,13,17.3,-51.12,0.98964,14,-41.76,-40.92,0.01036,1,13,-18.96,-70.94,1,1,13,-22.52,-71.33,1,1,13,-23.28,-70.27,1,1,13,-14.16,-54.98,1,1,13,-8.16,-41.19,1,1,13,-10.94,-38.36,1,2,13,8.5,34.28,0.86605,14,-25.88,43.45,0.13395,2,13,14.88,36.88,0.80824,14,-19.02,44.13,0.19176,2,13,18.02,54.05,0.72044,14,-11.12,59.69,0.27956,2,13,19.8,55.33,0.71958,14,-9.06,60.41,0.28042,2,13,33.52,49.27,0.64461,14,2.37,50.69,0.35539,2,13,47.5,43.09,0.42953,14,14.01,40.79,0.57047,2,13,69.23,33.49,0.07056,14,32.11,25.4,0.92944,1,14,53.62,7.12,1],"edges":[0,42,0,2,2,4,4,6,6,8,16,18,18,20,20,22,22,24,24,26,26,28,28,30,30,32,32,34,12,38,38,40,40,42,8,10,10,12,40,10,34,36,36,38,12,14,14,16,36,14]}},"8":{"8":{"type":"mesh","hull":20,"width":93,"height":148,"uvs":[0.27759,0,0.31548,0,0.47844,0.08352,0.65081,0.17187,0.76873,0.23231,0.90412,0.3017,1,0.35084,1,0.36662,0.81025,0.45774,0.79116,0.49203,0.85586,0.5531,0.40117,0.68828,0.28727,0.75883,0.08736,0.91816,0.0111,1,0,1,0,0.51703,0.04874,0.22998,0.14009,0.07978,0.26754,0.00038],"triangles":[3,9,17,2,17,18,17,2,3,1,2,18,18,19,0,18,0,1,14,15,13,15,16,13,13,16,12,12,16,11,11,16,9,17,9,16,11,9,10,8,9,3,8,3,4,8,5,7,8,4,5,5,6,7],"vertices":[1,16,48.35,-3.94,1,1,16,47.41,-7.33,1,2,15,71.13,-26.22,0.02368,16,31.43,-18.61,0.97632,2,15,51.68,-33.28,0.34893,16,14.52,-30.53,0.65107,2,15,38.38,-38.11,0.68513,16,2.96,-38.69,0.31487,2,15,23.11,-43.65,0.90379,16,-10.32,-48.06,0.09621,2,15,12.29,-47.58,0.94598,16,-19.72,-54.69,0.05402,2,15,10.29,-46.38,0.9468,16,-21.97,-54.06,0.0532,2,15,7.76,-24.31,0.9809,16,-30.21,-33.44,0.0191,2,15,4.31,-20.19,0.99552,16,-34.63,-30.37,0.00448,1,15,-6.53,-20.72,1,2,15,-2.03,25.84,0.99993,16,-52.85,12.37,0.00007,2,15,-5.56,40.29,0.99999,16,-60.06,25.38,0.00001,1,15,-16.27,68.34,1,1,15,-23.04,80.64,1,1,15,-22.51,81.53,1,2,15,38.86,44.88,0.83182,16,-18.41,41.5,0.16818,2,15,73.01,19.2,0.05702,16,21.29,25.71,0.94298,1,16,40.42,11.55,1,1,16,48.55,-3.02,1],"edges":[0,38,0,2,12,14,14,16,16,18,18,20,20,22,22,24,24,26,26,28,28,30,30,32,32,34,34,36,36,38,2,4,4,6,6,8,8,10,10,12]}},"9":{"9":{"x":56.83,"y":2.34,"rotation":161.57,"width":138,"height":114}},"10":{"10":{"x":21.55,"y":-3.49,"rotation":157.52,"width":124,"height":70}},"11":{"11":{"x":48.59,"y":0.66,"rotation":-91.46,"width":124,"height":106}},"12":{"12":{"type":"mesh","hull":12,"width":384,"height":292,"uvs":[1,0.47376,0.91048,0.72655,0.84817,0.90251,0.55009,1,0,1,0,0.19551,0.09498,0.13426,0.24935,0.22876,0.2729,0.18539,0.29592,0.14301,0.31189,0,1,0,0.33052,0.49651,0.49287,0.66801,0.63659,0.78176,0.55142,0.47551],"triangles":[12,7,8,15,12,8,13,12,15,14,13,15,1,14,15,2,14,1,5,12,4,7,5,6,12,5,7,3,13,14,4,12,13,3,4,13,3,14,2,9,10,11,0,9,11,15,9,0,8,9,15,1,15,0],"vertices":[1,6,111.19,-143.73,1,3,2,96.03,-167.59,0.01098,6,33.34,-167.59,0.48671,3,-189.71,-30.09,0.50231,3,2,41.85,-184.2,0.0054,6,-20.85,-184.2,0.30657,3,-185.6,26.44,0.68803,2,6,-118.62,-118.21,0.03367,3,-88.72,93.72,0.96633,1,3,108.73,168.77,1,3,2,-22.76,195.96,0.00361,6,-85.46,195.96,0.00047,3,192.2,-50.81,0.99592,3,2,14.94,180.83,0.0186,6,-47.76,180.83,0.01052,3,164.46,-80.49,0.97087,3,2,34.11,118.32,0.18441,6,-28.59,118.32,0.18929,3,99.24,-75.76,0.62629,3,2,49.58,120.08,0.23972,6,-13.12,120.08,0.33813,3,95.29,-90.81,0.42215,1,6,1.99,121.79,1,1,6,37.12,145.19,1,2,6,213.97,-51.14,0.99703,3,-146.46,-240.62,0.00297,3,2,-3.12,42.83,0.2026,6,-65.81,42.83,0.01371,3,42.33,-13.75,0.78368,2,6,-61.3,-37,0.0182,3,-33.74,10.91,0.9818,3,2,13.66,-100.24,0.02313,6,-49.04,-100.24,0.15031,3,-97.13,22.35,0.82656,3,2,58.22,-16.09,0.55032,6,-4.48,-16.09,0.33999,3,-34.78,-49.62,0.10969],"edges":[14,24,24,26,26,28,28,4,6,8,4,6,20,22,18,20,0,22,18,0,14,16,16,18,16,30,0,2,2,4,30,2,14,12,8,10,12,10]}},"13":{"13":{"x":58.28,"y":-3.48,"rotation":173.13,"width":142,"height":98}},"14":{"14":{"x":75.11,"y":-7.85,"rotation":88.13,"width":89,"height":183}},"maozi_1":{"maozi":{"x":-4.1,"y":2.69,"rotation":-82.48,"width":312,"height":136}},"maozi_2":{"maozi":{"x":-4.1,"y":2.69,"rotation":-82.48,"width":312,"height":136}}}}],"animations":{"animation":{"slots":{"4":{"attachment":[{"time":1,"name":"4"},{"time":1.0667,"name":"4_1"}]}},"bones":{"2":{"rotate":[{"angle":-1.72,"curve":0.382,"c2":0.57,"c3":0.735},{"time":0.1667,"curve":0.25,"c3":0.75},{"time":0.6667,"angle":-6.06,"curve":0.243,"c3":0.649,"c4":0.6},{"time":1,"angle":-1.72,"curve":0.382,"c2":0.57,"c3":0.735},{"time":1.1667,"curve":0.25,"c3":0.75},{"time":1.6667,"angle":-6.06,"curve":0.243,"c3":0.649,"c4":0.6},{"time":2,"angle":-1.72}],"translate":[{"x":-2.24,"y":-1.81,"curve":0.382,"c2":0.57,"c3":0.735},{"time":0.1667,"curve":0.25,"c3":0.75},{"time":0.6667,"x":-7.9,"y":-6.37,"curve":0.243,"c3":0.649,"c4":0.6},{"time":1,"x":-2.24,"y":-1.81,"curve":0.382,"c2":0.57,"c3":0.735},{"time":1.1667,"curve":0.25,"c3":0.75},{"time":1.6667,"x":-7.9,"y":-6.37,"curve":0.243,"c3":0.649,"c4":0.6},{"time":2,"x":-2.24,"y":-1.81}]},"4":{"rotate":[{"angle":1.43,"curve":0.372,"c2":0.48,"c3":0.752},{"time":0.2667,"angle":2.45,"curve":0.25,"c3":0.75},{"time":0.7667,"angle":0.57,"curve":0.252,"c3":0.622,"c4":0.48},{"time":1,"angle":1.43,"curve":0.372,"c2":0.48,"c3":0.752},{"time":1.2667,"angle":2.45,"curve":0.25,"c3":0.75},{"time":1.7667,"angle":0.57,"curve":0.252,"c3":0.622,"c4":0.48},{"time":2,"angle":1.43}]},"5":{"translate":[{"curve":0.25,"c3":0.75},{"time":0.5,"x":-0.12,"y":2.9,"curve":0.25,"c3":0.75},{"time":1,"curve":0.25,"c3":0.75},{"time":1.5,"x":-0.12,"y":2.9,"curve":0.25,"c3":0.75},{"time":2}]},"6":{"rotate":[{"angle":1.33,"curve":0.351,"c2":0.4,"c3":0.757},{"time":0.3333,"curve":0.25,"c3":0.75},{"time":0.8333,"angle":1.85,"curve":0.265,"c3":0.618,"c4":0.43},{"time":1,"angle":1.33,"curve":0.351,"c2":0.4,"c3":0.757},{"time":1.3333,"curve":0.25,"c3":0.75},{"time":1.8333,"angle":1.85,"curve":0.265,"c3":0.618,"c4":0.43},{"time":2,"angle":1.33}]},"7":{"translate":[{"x":12.31,"y":0.54,"curve":0.25,"c3":0.75},{"time":0.5,"curve":0.25,"c3":0.75},{"time":1,"x":12.31,"y":0.54,"curve":0.25,"c3":0.75},{"time":1.5,"curve":0.25,"c3":0.75},{"time":2,"x":12.31,"y":0.54}]},"8":{"rotate":[{"angle":2.93,"curve":0.382,"c2":0.57,"c3":0.735},{"time":0.1667,"angle":7.45,"curve":0.25,"c3":0.75},{"time":0.6667,"angle":-8.46,"curve":0.243,"c3":0.649,"c4":0.6},{"time":1,"angle":2.93,"curve":0.382,"c2":0.57,"c3":0.735},{"time":1.1667,"angle":7.45,"curve":0.25,"c3":0.75},{"time":1.6667,"angle":-8.46,"curve":0.243,"c3":0.649,"c4":0.6},{"time":2,"angle":2.93}],"translate":[{"x":-3.77,"y":2.95,"curve":0.382,"c2":0.57,"c3":0.735},{"time":0.1667,"x":-5.26,"y":4.12,"curve":0.25,"c3":0.75},{"time":0.6667,"curve":0.243,"c3":0.649,"c4":0.6},{"time":1,"x":-3.77,"y":2.95,"curve":0.382,"c2":0.57,"c3":0.735},{"time":1.1667,"x":-5.26,"y":4.12,"curve":0.25,"c3":0.75},{"time":1.6667,"curve":0.243,"c3":0.649,"c4":0.6},{"time":2,"x":-3.77,"y":2.95}]},"9":{"rotate":[{"angle":-11.19,"curve":0.25,"c3":0.75},{"time":0.5,"curve":0.25,"c3":0.75},{"time":1,"angle":-11.19,"curve":0.25,"c3":0.75},{"time":1.5,"curve":0.25,"c3":0.75},{"time":2,"angle":-11.19}],"translate":[{"x":2.46,"y":-11.08,"curve":0.25,"c3":0.75},{"time":0.5,"x":3.13,"y":-8.89,"curve":0.25,"c3":0.75},{"time":1,"x":2.46,"y":-11.08,"curve":0.25,"c3":0.75},{"time":1.5,"x":3.13,"y":-8.89,"curve":0.25,"c3":0.75},{"time":2,"x":2.46,"y":-11.08}]},"10":{"rotate":[{"angle":-3.95,"curve":0.351,"c2":0.4,"c3":0.757},{"time":0.3333,"angle":7.45,"curve":0.25,"c3":0.75},{"time":0.8333,"angle":-8.46,"curve":0.265,"c3":0.618,"c4":0.43},{"time":1,"angle":-3.95,"curve":0.351,"c2":0.4,"c3":0.757},{"time":1.3333,"angle":7.45,"curve":0.25,"c3":0.75},{"time":1.8333,"angle":-8.46,"curve":0.265,"c3":0.618,"c4":0.43},{"time":2,"angle":-3.95}]},"11":{"rotate":[{"angle":-5.1,"curve":0.375,"c2":0.62,"c3":0.716},{"time":0.1,"angle":-5.86,"curve":0.25,"c3":0.75},{"time":0.6,"curve":0.243,"c3":0.68,"c4":0.71},{"time":1,"angle":-5.1,"curve":0.375,"c2":0.62,"c3":0.716},{"time":1.1,"angle":-5.86,"curve":0.25,"c3":0.75},{"time":1.6,"curve":0.243,"c3":0.68,"c4":0.71},{"time":2,"angle":-5.1}]},"16":{"rotate":[{"angle":-2.15,"curve":0.372,"c2":0.48,"c3":0.752},{"time":0.2667,"curve":0.25,"c3":0.75},{"time":0.7667,"angle":-3.96,"curve":0.252,"c3":0.622,"c4":0.48},{"time":1,"angle":-2.15,"curve":0.372,"c2":0.48,"c3":0.752},{"time":1.2667,"curve":0.25,"c3":0.75},{"time":1.7667,"angle":-3.96,"curve":0.252,"c3":0.622,"c4":0.48},{"time":2,"angle":-2.15}]},"18":{"rotate":[{"angle":-3.86,"curve":0.382,"c2":0.57,"c3":0.735},{"time":0.1667,"angle":-8.27,"curve":0.25,"c3":0.75},{"time":0.6667,"angle":7.27,"curve":0.243,"c3":0.649,"c4":0.6},{"time":1,"angle":-3.86,"curve":0.382,"c2":0.57,"c3":0.735},{"time":1.1667,"angle":-8.27,"curve":0.25,"c3":0.75},{"time":1.6667,"angle":7.27,"curve":0.243,"c3":0.649,"c4":0.6},{"time":2,"angle":-3.86}],"translate":[{"x":-3.52,"y":-2.75,"curve":0.382,"c2":0.57,"c3":0.735},{"time":0.1667,"x":-4.91,"y":-3.85,"curve":0.25,"c3":0.75},{"time":0.6667,"curve":0.243,"c3":0.649,"c4":0.6},{"time":1,"x":-3.52,"y":-2.75,"curve":0.382,"c2":0.57,"c3":0.735},{"time":1.1667,"x":-4.91,"y":-3.85,"curve":0.25,"c3":0.75},{"time":1.6667,"curve":0.243,"c3":0.649,"c4":0.6},{"time":2,"x":-3.52,"y":-2.75}]},"19":{"rotate":[{"angle":2.86,"curve":0.351,"c2":0.4,"c3":0.757},{"time":0.3333,"angle":-8.27,"curve":0.25,"c3":0.75},{"time":0.8333,"angle":7.27,"curve":0.265,"c3":0.618,"c4":0.43},{"time":1,"angle":2.86,"curve":0.351,"c2":0.4,"c3":0.757},{"time":1.3333,"angle":-8.27,"curve":0.25,"c3":0.75},{"time":1.8333,"angle":7.27,"curve":0.265,"c3":0.618,"c4":0.43},{"time":2,"angle":2.86}]},"21":{"translate":[{"curve":0.25,"c3":0.75},{"time":0.5,"x":-0.09,"y":2.17,"curve":0.25,"c3":0.75},{"time":1,"curve":0.25,"c3":0.75},{"time":1.5,"x":-0.09,"y":2.17,"curve":0.25,"c3":0.75},{"time":2}]},"13b":{"rotate":[{"angle":0.89,"curve":0.382,"c2":0.57,"c3":0.735},{"time":0.1667,"curve":0.25,"c3":0.75},{"time":0.6667,"angle":3.13,"curve":0.243,"c3":0.649,"c4":0.6},{"time":1,"angle":0.89,"curve":0.382,"c2":0.57,"c3":0.735},{"time":1.1667,"curve":0.25,"c3":0.75},{"time":1.6667,"angle":3.13,"curve":0.243,"c3":0.649,"c4":0.6},{"time":2,"angle":0.89}],"translate":[{"x":1.1,"y":-1.22,"curve":0.382,"c2":0.57,"c3":0.735},{"time":0.1667,"curve":0.25,"c3":0.75},{"time":0.6667,"x":3.88,"y":-4.31,"curve":0.243,"c3":0.649,"c4":0.6},{"time":1,"x":1.1,"y":-1.22,"curve":0.382,"c2":0.57,"c3":0.735},{"time":1.1667,"curve":0.25,"c3":0.75},{"time":1.6667,"x":3.88,"y":-4.31,"curve":0.243,"c3":0.649,"c4":0.6},{"time":2,"x":1.1,"y":-1.22}]}},"deform":{"default":{"1":{"1":[{"curve":0.25,"c3":0.75,"vertices":[1.16993,-1.65387,-0.54737,0.08982,-0.51382,0.32809,0,0,2.83196,0.57166,2.1124,-2.85163,2.03514,2.04058,5.00081,-0.72446,0,0,0,0,1.42832,-1.50973,5.79023,-2.84856,7.07403,-1.30646,6.79734,0.57955,1.45273,-0.2565,0,0,0,0,0,0,0,0,-1.83419,-0.12393,-0.99636,0.08188,1.17487,-0.77445,1.08377,-0.92941]},{"time":0.5,"curve":0.25,"c3":0.75,"vertices":[-6.97385,0.68336,-4.63629,0.26402,-5.24982,0.80002,0,0,0,0,-9.19504,-0.62127,-9.19504,-0.62127,0,0,0,0,0,0,-5.74686,-0.38828,-5.74686,-0.38828,-5.74686,-0.38828,-5.74686,-0.38828,-5.74686,-0.38828,0,0,0,0,0,0,0,0,-4.02277,-0.27181,-6.32159,-0.42714,-5.66913,-1.53765,-9.92493,1.63864]},{"time":1,"curve":0.25,"c3":0.75,"vertices":[1.16993,-1.65387,-0.54737,0.08982,-0.51382,0.32809,0,0,2.83196,0.57166,2.1124,-2.85163,2.03514,2.04058,5.00081,-0.72446,0,0,0,0,1.42832,-1.50973,5.79023,-2.84856,7.07403,-1.30646,6.79734,0.57955,1.45273,-0.2565,0,0,0,0,0,0,0,0,-1.83419,-0.12393,-0.99636,0.08188,1.17487,-0.77445,1.08377,-0.92941]},{"time":1.5,"curve":0.25,"c3":0.75,"vertices":[-6.97385,0.68336,-4.63629,0.26402,-5.24982,0.80002,0,0,0,0,-9.19504,-0.62127,-9.19504,-0.62127,0,0,0,0,0,0,-5.74686,-0.38828,-5.74686,-0.38828,-5.74686,-0.38828,-5.74686,-0.38828,-5.74686,-0.38828,0,0,0,0,0,0,0,0,-4.02277,-0.27181,-6.32159,-0.42714,-5.66913,-1.53765,-9.92493,1.63864]},{"time":2,"vertices":[1.16993,-1.65387,-0.54737,0.08982,-0.51382,0.32809,0,0,2.83196,0.57166,2.1124,-2.85163,2.03514,2.04058,5.00081,-0.72446,0,0,0,0,1.42832,-1.50973,5.79023,-2.84856,7.07403,-1.30646,6.79734,0.57955,1.45273,-0.2565,0,0,0,0,0,0,0,0,-1.83419,-0.12393,-0.99636,0.08188,1.17487,-0.77445,1.08377,-0.92941]}]}}}}}}]],0,0,[],[],[]]
